{
  "contacts": [
    {
      "id":1,
      "Name": "L. Messi",
      "Age": 31,
      "image": "https://images.news18.com/ibnlive/uploads/2021/07/1626000118_lionel-messi-afp-1200.jpg?impolicy=website&width=510&height=356",
      "Nationality": "Argentina",
      "Overall": 94,
      "Club": "FC Barcelona",
      "Value": "€110.5M",
      "Wage": "€565K",
      "PreferredFoot": "Left",
      "Work Rate": "Medium/ Medium",
      "Position": "RF",
      "JerseyNumber": 10,
      "Joined": "1-Jul-04",
      "Contract Valid Until": 2021,
      "Height": "5'7",
      "Weight": "159lbs",
      "Crossing": 84,
      "Finishing": 95,
      "HeadingAccuracy": 70,
      "ShortPassing": 90,
      "Volleys": 86
    },
    {
      "id":2,
      "Name": "Cristiano Ronaldo",
      "Age": 33,
      "image": "https://thumbor.forbes.com/thumbor/fit-in/416x416/filters%3Aformat%28jpg%29/https%3A%2F%2Fspecials-images.forbesimg.com%2Fimageserve%2F5ec593cc431fb70007482137%2F0x0.jpg%3Fbackground%3D000000%26cropX1%3D1321%26cropX2%3D3300%26cropY1%3D114%26cropY2%3D2093",
      "Nationality": "Portugal",
      "Overall": 94,
      "Club": "Juventus",
      "Value": "€77M",
      "Wage": "€405K",
      "PreferredFoot": "Right",
      "Work Rate": "High/ Low",
      "Position": "ST",
      "JerseyNumber": 7,
      "Joined": "10-Jul-18",
      "Contract Valid Until": 2022,
      "Height": "6'2",
      "Weight": "183lbs",
      "Crossing": 84,
      "Finishing": 94,
      "HeadingAccuracy": 89,
      "ShortPassing": 81,
      "Volleys": 87
    },
    {
      "id":3,
      "Name": "Neymar Jr",
      "Age": 26,
      "image": "https://borgenmagazine.com/wp-content/uploads/2019/05/Neymar.jpeg",
      "Nationality": "Brazil",
      "Overall": 92,
      "Club": "Paris Saint-Germain",
      "Value": "€118.5M",
      "Wage": "€290K",
      "PreferredFoot": "Right",
      "Work Rate": "High/ Medium",
      "Position": "LW",
      "JerseyNumber": 10,
      "Joined": "3-Aug-17",
      "Contract Valid Until": 2022,
      "Height": "5'9",
      "Weight": "150lbs",
      "Crossing": 79,
      "Finishing": 87,
      "HeadingAccuracy": 62,
      "ShortPassing": 84,
      "Volleys": 84
    },
    {
      "id":4,
      "Name": "De Gea",
      "Age": 27,
      "image": "https://thumbor.forbes.com/thumbor/fit-in/416x416/filters%3Aformat%28jpg%29/https%3A%2F%2Fspecials-images.forbesimg.com%2Fimageserve%2F5ec7036e343cbb00069deee6%2F0x0.jpg%3Fbackground%3D000000%26cropX1%3D582%26cropX2%3D2340%26cropY1%3D47%26cropY2%3D1804",
      "Nationality": "Spain",
      "Overall": 91,
      "Club": "Manchester United",
      "Value": "€72M",
      "Wage": "€260K",
      "PreferredFoot": "Right",
      "Work Rate": "Medium/ Medium",
      "Position": "GK",
      "JerseyNumber": 1,
      "Joined": "1-Jul-11",
      "Contract Valid Until": 2020,
      "Height": "6'4",
      "Weight": "168lbs",
      "Crossing": 17,
      "Finishing": 13,
      "HeadingAccuracy": 21,
      "ShortPassing": 50,
      "Volleys": 13
    },
    {
      "Name": "K. De Bruyne",
      "Age": 27,
      "image": "https://img.a.transfermarkt.technology/portrait/header/88755-1626449012.jpg?lm=1",
      "Nationality": "Belgium",
      "Overall": 91,
      "Club": "Manchester City",
      "Value": "€102M",
      "Wage": "€355K",
      "PreferredFoot": "Right",
      "Work Rate": "High/ High",
      "Position": "RCM",
      "JerseyNumber": 7,
      "Joined": "30-Aug-15",
      "Contract Valid Until": 2023,
      "Height": "5'11",
      "Weight": "154lbs",
      "Crossing": 93,
      "Finishing": 82,
      "HeadingAccuracy": 55,
      "ShortPassing": 92,
      "Volleys": 82
    }
  ]
}